huaweicloudsdkcloudrtc/__init__.py
huaweicloudsdkcloudrtc/v1/__init__.py
huaweicloudsdkcloudrtc/v1/cloudrtc_async_client.py
huaweicloudsdkcloudrtc/v1/cloudrtc_client.py
huaweicloudsdkcloudrtc/v1/model/__init__.py
huaweicloudsdkcloudrtc/v1/model/abnormal_event.py
huaweicloudsdkcloudrtc/v1/model/abnormal_event_dimension_value.py
huaweicloudsdkcloudrtc/v1/model/list_rtc_abnormal_event_dimension_request.py
huaweicloudsdkcloudrtc/v1/model/list_rtc_abnormal_event_dimension_response.py
huaweicloudsdkcloudrtc/v1/model/list_rtc_abnormal_event_request.py
huaweicloudsdkcloudrtc/v1/model/list_rtc_abnormal_event_response.py
huaweicloudsdkcloudrtc/v1/model/list_rtc_abnormal_events_request.py
huaweicloudsdkcloudrtc/v1/model/list_rtc_abnormal_events_response.py
huaweicloudsdkcloudrtc/v1/model/list_rtc_client_qos_details_request.py
huaweicloudsdkcloudrtc/v1/model/list_rtc_client_qos_details_response.py
huaweicloudsdkcloudrtc/v1/model/list_rtc_event_request.py
huaweicloudsdkcloudrtc/v1/model/list_rtc_event_response.py
huaweicloudsdkcloudrtc/v1/model/list_rtc_history_quality_request.py
huaweicloudsdkcloudrtc/v1/model/list_rtc_history_quality_response.py
huaweicloudsdkcloudrtc/v1/model/list_rtc_history_scale_request.py
huaweicloudsdkcloudrtc/v1/model/list_rtc_history_scale_response.py
huaweicloudsdkcloudrtc/v1/model/list_rtc_history_usage_request.py
huaweicloudsdkcloudrtc/v1/model/list_rtc_history_usage_response.py
huaweicloudsdkcloudrtc/v1/model/list_rtc_realtime_network_request.py
huaweicloudsdkcloudrtc/v1/model/list_rtc_realtime_network_response.py
huaweicloudsdkcloudrtc/v1/model/list_rtc_realtime_quality_request.py
huaweicloudsdkcloudrtc/v1/model/list_rtc_realtime_quality_response.py
huaweicloudsdkcloudrtc/v1/model/list_rtc_realtime_scale_dimension_request.py
huaweicloudsdkcloudrtc/v1/model/list_rtc_realtime_scale_dimension_response.py
huaweicloudsdkcloudrtc/v1/model/list_rtc_realtime_scale_request.py
huaweicloudsdkcloudrtc/v1/model/list_rtc_realtime_scale_response.py
huaweicloudsdkcloudrtc-3.1.184.dist-info/METADATA
huaweicloudsdkcloudrtc-3.1.184.dist-info/WHEEL
huaweicloudsdkcloudrtc-3.1.184.dist-info/licenses/LICENSE
huaweicloudsdkcloudrtc-3.1.184.dist-info/RECORD
